ecm_thinkclock/__init__.py
ecm_thinkclock/cell_discharge_data.py
ecm_thinkclock/cell_ecm.py
ecm_thinkclock/cell_hppc_data.py
ecm_thinkclock/cell_temperature_data.py
ecm_thinkclock/module_ecm.py
ecm_thinkclock/module_hppc_data.py
ecm_thinkclock/pack_us06_data.py
ecm_thinkclock/thermal_model.py
ecm_thinkclock/utils.py
ecm_thinkclock-20.3.dist-info/LICENSE
ecm_thinkclock-20.3.dist-info/METADATA
ecm_thinkclock-20.3.dist-info/WHEEL
ecm_thinkclock-20.3.dist-info/top_level.txt
ecm_thinkclock-20.3.dist-info/RECORD
