Metadata-Version: 2.1
Name: ecm-thinkclock
Version: 20.3
Summary: A Python package for equivalent circuit models
Home-page: https://github.com/batterysim/equiv-circ-model
Author: Gavin Wiggins
Classifier: Programming Language :: Python :: 3
Classifier: License :: OSI Approved :: MIT License
Classifier: Operating System :: OS Independent
License-File: LICENSE
Requires-Dist: matplotlib
Requires-Dist: numpy
Requires-Dist: pandas
Requires-Dist: scipy
